escrow_includes/__init__.py
"escrow_includes/app_services/__init__,py"
escrow_includes/errors/__init__.py
escrow_includes/errors/exception_handler.py
escrow_includes/errors/exceptions.py
escrow_includes/helpers/__init__.py
escrow_includes/helpers/drf_helpers/__init__.py
escrow_includes/helpers/drf_helpers/models.py
escrow_includes/helpers/drf_helpers/pagination.py
escrow_includes/helpers/drf_helpers/serializers.py
escrow_includes/helpers/utils.py
escrow_includes-0.1.1.dist-info/WHEEL
escrow_includes-0.1.1.dist-info/METADATA
escrow_includes-0.1.1.dist-info/RECORD
