Metadata-Version: 2.1
Name: escrow-includes
Version: 0.1.1
Summary: general lib utils for escrow backend service
Author: o4codes
Author-email: oforkansi.shadrach@gmail.com
Requires-Python: >=3.9,<4.0
Classifier: Programming Language :: Python :: 3
Classifier: Programming Language :: Python :: 3.10
Classifier: Programming Language :: Python :: 3.9
Requires-Dist: Django (>=4.2.7,<5.0.0)
Requires-Dist: djangorestframework (>=3.14.0,<4.0.0)
Requires-Dist: pydantic (==1.10)
